streamlit_chunk_file_uploader/__init__.py
streamlit_chunk_file_uploader/_models.py
streamlit_chunk_file_uploader/_utils.py
streamlit_chunk_file_uploader/_version.py
streamlit_chunk_file_uploader/frontend/.prettierrc
streamlit_chunk_file_uploader/frontend/package-lock.json
streamlit_chunk_file_uploader/frontend/package.json
streamlit_chunk_file_uploader/frontend/tsconfig.json
streamlit_chunk_file_uploader/frontend/build/asset-manifest.json
streamlit_chunk_file_uploader/frontend/build/bootstrap.min.css
streamlit_chunk_file_uploader/frontend/build/index.html
streamlit_chunk_file_uploader/frontend/build/static/js/main.92397d37.js
streamlit_chunk_file_uploader/frontend/build/static/js/main.92397d37.js.LICENSE.txt
streamlit_chunk_file_uploader/frontend/build/static/js/main.92397d37.js.map
streamlit_chunk_file_uploader/frontend/public/bootstrap.min.css
streamlit_chunk_file_uploader/frontend/public/index.html
streamlit_chunk_file_uploader/frontend/src/FileUploader.tsx
streamlit_chunk_file_uploader/frontend/src/index.tsx
streamlit_chunk_file_uploader/frontend/src/react-app-env.d.ts
streamlit_chunk_file_uploader-1.0.4.dist-info/LICENSE
streamlit_chunk_file_uploader-1.0.4.dist-info/METADATA
streamlit_chunk_file_uploader-1.0.4.dist-info/WHEEL
streamlit_chunk_file_uploader-1.0.4.dist-info/top_level.txt
streamlit_chunk_file_uploader-1.0.4.dist-info/RECORD
